holodeck/__init__.py
holodeck/agents.py
holodeck/command.py
holodeck/environments.py
holodeck/exceptions.py
holodeck/holodeck.py
holodeck/holodeckclient.py
holodeck/joint_constraints.py
holodeck/packagemanager.py
holodeck/sensors.py
holodeck/shmem.py
holodeck/spaces.py
holodeck/util.py
holodeck/weather.py
holodeck-0.3.1.dist-info/LICENSE
holodeck-0.3.1.dist-info/METADATA
holodeck-0.3.1.dist-info/WHEEL
holodeck-0.3.1.dist-info/top_level.txt
holodeck-0.3.1.dist-info/RECORD
