Metadata-Version: 2.1
Name: holodeck
Version: 0.3.1
Summary: High fidelity simulated environments for reinforcement learning
Home-page: https://github.com/byu-pccl/holodeck
Author: Joshua Greaves, Max Robinson, Nick Walton, Jayden Milne, Vin Howe, Daniel Ekpo, Kolby Nottingham
Author-email: holodeck@cs.byu.edu
License: MIT License
Platform: UNKNOWN
Requires-Python: >=3.5
Requires-Dist: numpy
Requires-Dist: posix-ipc (>=1.0.0) ; platform_system == "Linux"
Requires-Dist: pywin32 (>=1.0) ; platform_system == "Windows"
